[
 {
  "Asin": "4813710182",
  "URL": "https://www.amazon.co.jp/dp/4813710182?tag=99hatena-22&linkCode=ogi&th=1&psc=1",
  "ImageURL": "なし",
  "Publisher": "スターツ出版",
  "Contributor": "瑞希ちこ(著)",
  "Booktype": "文庫",
  "Title": "(仮)転生モブ令嬢の本領発揮~占いにごはん、時々もふもふはじめました!~ (ベリーズ文庫)",
  "Price": 704,
  "Category": "ジャンル別,Featured Categories",
  "Points": 7
 },
 {
  "Asin": "4403525229",
  "URL": "https://www.amazon.co.jp/dp/4403525229?tag=99hatena-22&linkCode=ogi&th=1&psc=1",
  "ImageURL": "なし",
  "Publisher": "新書館",
  "Contributor": "夕映 月子(著)",
  "Booktype": "文庫",
  "Title": "あなたを好きになりたくない (ディアプラス文庫)",
  "Price": 748,
  "Category": "ボーイズラブノベルス,Featured Categories",
  "Points": 7
 },
 {
  "Asin": "419894606X",
  "URL": "https://www.amazon.co.jp/dp/419894606X?tag=99hatena-22&linkCode=ogi&th=1&psc=1",
  "ImageURL": "なし",
  "Publisher": "徳間書店",
  "Contributor": "北森鴻(著)",
  "Booktype": "文庫",
  "Title": "旗師・冬狐堂二 狐闇 (徳間文庫)",
  "Price": 880,
  "Category": "ジャンル別,Featured Categories",
  "Points": 9
 },
 {
  "Asin": "481371014X",
  "URL": "https://www.amazon.co.jp/dp/481371014X?tag=99hatena-22&linkCode=ogi&th=1&psc=1",
  "ImageURL": "なし",
  "Publisher": "スターツ出版",
  "Contributor": "きたみまゆ(著)",
  "Booktype": "文庫",
  "Title": "(仮)予想外の妊娠ですが、なんとしても隠し通そうと思います。 (ベリーズ文庫)",
  "Price": 704,
  "Category": "ジャンル別,Featured Categories",
  "Points": 7
 },
 {
  "Asin": "4198946108",
  "URL": "https://www.amazon.co.jp/dp/4198946108?tag=99hatena-22&linkCode=ogi&th=1&psc=1",
  "ImageURL": "なし",
  "Publisher": "徳間書店",
  "Contributor": "宮本昌孝(著)",
  "Booktype": "文庫",
  "Title": "乱丸上: 新装版 (徳間文庫)",
  "Price": 880,
  "Category": "ジャンル別,Featured Categories",
  "Points": 9
 },
 {
  "Asin": "4198946124",
  "URL": "https://www.amazon.co.jp/dp/4198946124?tag=99hatena-22&linkCode=ogi&th=1&psc=1",
  "ImageURL": "なし",
  "Publisher": "徳間書店",
  "Contributor": "六道慧(著)",
  "Booktype": "文庫",
  "Title": "警視庁特殊詐欺追跡班 マトリの男 (徳間文庫)",
  "Price": "なし",
  "Category": "ジャンル別,Featured Categories",
  "Points": 9
 },
 {
  "Asin": "4908957150",
  "URL": "https://www.amazon.co.jp/dp/4908957150?tag=99hatena-22&linkCode=ogi&th=1&psc=1",
  "ImageURL": "https://m.media-amazon.com/images/I/51j0k4D+9+L.jpg",
  "Publisher": "桜山社",
  "Contributor": "佐藤 啓(著)",
  "Booktype": "単行本",
  "Title": "無名の開幕投手 高橋ユニオンズエース・滝良彦の軌跡",
  "Price": 2640,
  "Category": "スポーツ",
  "Points": 26
 },
 {
  "Asin": "4877232656",
  "URL": "https://www.amazon.co.jp/dp/4877232656?tag=99hatena-22&linkCode=ogi&th=1&psc=1",
  "ImageURL": "なし",
  "Publisher": "興陽館",
  "Contributor": "渋沢 栄一(著)",
  "Booktype": "単行本（ソフトカバー）",
  "Title": "論語と算盤―渋沢栄一の名著を「生の言葉」で読む。",
  "Price": 1100,
  "Category": "東洋哲学入門",
  "Points": 11
 },
 {
  "Asin": "4756252524",
  "URL": "https://www.amazon.co.jp/dp/4756252524?tag=99hatena-22&linkCode=ogi&th=1&psc=1",
  "ImageURL": "https://m.media-amazon.com/images/I/41GadN7t4xL.jpg",
  "Publisher": "パイインターナショナル",
  "Contributor": "西澤 明洋(著)",
  "Booktype": "単行本（ソフトカバー）",
  "Title": "ブランディングデザインの教科書",
  "Price": 1760,
  "Category": "デザイン",
  "Points": 18
 },
 {
  "Asin": "4295404047",
  "URL": "https://www.amazon.co.jp/dp/4295404047?tag=99hatena-22&linkCode=ogi&th=1&psc=1",
  "ImageURL": "https://m.media-amazon.com/images/I/41UrSqrUeTL.jpg",
  "Publisher": "クロスメディア・パブリッシング(インプレス)",
  "Contributor": "グラナダ (編著)(著)",
  "Booktype": "単行本（ソフトカバー）",
  "Title": "COOK JAPAN PROJECT",
  "Price": 3278,
  "Category": "グルメ一般",
  "Points": 33
 },
 {
  "Asin": "4815605254",
  "URL": "https://www.amazon.co.jp/dp/4815605254?tag=99hatena-22&linkCode=ogi&th=1&psc=1",
  "ImageURL": "https://m.media-amazon.com/images/I/51HObYBLXUL.jpg",
  "Publisher": "SBクリエイティブ",
  "Contributor": "蒼機 純(著)",
  "Booktype": "文庫",
  "Title": "その商人の弟子、剣につき (GA文庫)",
  "Price": 715,
  "Category": "ライトノベル,Featured Categories",
  "Points": 12
 },
 {
  "Asin": "4797397187",
  "URL": "https://www.amazon.co.jp/dp/4797397187?tag=99hatena-22&linkCode=ogi&th=1&psc=1",
  "ImageURL": "https://m.media-amazon.com/images/I/51UhPnff29L.jpg",
  "Publisher": "SBクリエイティブ",
  "Contributor": "河森正治(著)",
  "Booktype": "単行本",
  "Title": "マクロス 河森正治デザイナーズノート",
  "Price": 7260,
  "Category": "兵器・戦闘機,空襲,模型・プラモデル,収集・コレクション,ラジコン,イラスト集・オフィシャルブック,コミック・アニメ研究,一般",
  "Points": 132
 },
 {
  "Asin": "481560780X",
  "URL": "https://www.amazon.co.jp/dp/481560780X?tag=99hatena-22&linkCode=ogi&th=1&psc=1",
  "ImageURL": "https://m.media-amazon.com/images/I/51QS+TMM4bL.jpg",
  "Publisher": "SBクリエイティブ",
  "Contributor": "三河ごーすと(著)",
  "Booktype": "文庫",
  "Title": "友達の妹が俺にだけウザい6 小冊子付き特装版 (GA文庫)",
  "Price": 1089,
  "Category": "ライトノベル,Featured Categories",
  "Points": 11
 },
 {
  "Asin": "479806176X",
  "URL": "https://www.amazon.co.jp/dp/479806176X?tag=99hatena-22&linkCode=ogi&th=1&psc=1",
  "ImageURL": "なし",
  "Publisher": "秀和システム",
  "Contributor": "松浦健一郎(著)",
  "Booktype": "単行本",
  "Title": "Pythonでつくるゲームプログラミング入門",
  "Price": 2860,
  "Category": "ゲームプログラミング",
  "Points": 29
 },
 {
  "Asin": "4756253423",
  "URL": "https://www.amazon.co.jp/dp/4756253423?tag=99hatena-22&linkCode=ogi&th=1&psc=1",
  "ImageURL": "なし",
  "Publisher": "パイインターナショナル",
  "Contributor": "海野 弘(著)",
  "Booktype": "単行本（ソフトカバー）",
  "Title": "ロンドンの誘惑 1970's ロンドン・カルチャーの世界",
  "Price": 4180,
  "Category": "モード",
  "Points": 42
 },
 {
  "Asin": "4801971431",
  "URL": "https://www.amazon.co.jp/dp/4801971431?tag=99hatena-22&linkCode=ogi&th=1&psc=1",
  "ImageURL": "なし",
  "Publisher": "竹書房",
  "Contributor": "真鍋譲治(著)",
  "Booktype": "コミック",
  "Title": "パトラと鉄十字 (3) (バンブーコミックス)",
  "Price": 726,
  "Category": "コミック",
  "Points": 7
 },
 {
  "Asin": "4757569203",
  "URL": "https://www.amazon.co.jp/dp/4757569203?tag=99hatena-22&linkCode=ogi&th=1&psc=1",
  "ImageURL": "https://m.media-amazon.com/images/I/31xNJImoBIL.jpg",
  "Publisher": "スクウェア・エニックス",
  "Contributor": "桜井海(著)",
  "Booktype": "コミック",
  "Title": "おじさまと猫(6) (GCp)",
  "Price": 900,
  "Category": "コミック",
  "Points": 9
 },
 {
  "Asin": "4757569211",
  "URL": "https://www.amazon.co.jp/dp/4757569211?tag=99hatena-22&linkCode=ogi&th=1&psc=1",
  "ImageURL": "https://m.media-amazon.com/images/I/51Bavec2PTL.jpg",
  "Publisher": "スクウェア・エニックス",
  "Contributor": "桜井海(著)",
  "Booktype": "コミック",
  "Title": "おじさまと猫(6) ミニ画集付き特装版 (SEコミックスプレミアム)",
  "Price": 1400,
  "Category": "コミック",
  "Points": 14
 },
 {
  "Asin": "4046040815",
  "URL": "https://www.amazon.co.jp/dp/4046040815?tag=99hatena-22&linkCode=ogi&th=1&psc=1",
  "ImageURL": "https://m.media-amazon.com/images/I/51mQrnZwrqL.jpg",
  "Publisher": "KADOKAWA",
  "Contributor": "kazuma(著)",
  "Booktype": "単行本",
  "Title": "今すぐ使えて、会話がはずむ 今日のタメ口英語2",
  "Price": 1210,
  "Category": "英語",
  "Points": 22
 },
 {
  "Asin": "4760830421",
  "URL": "https://www.amazon.co.jp/dp/4760830421?tag=99hatena-22&linkCode=ogi&th=1&psc=1",
  "ImageURL": "なし",
  "Publisher": "金子書房",
  "Contributor": "村中直人(著)",
  "Booktype": "単行本",
  "Title": "ニューロダイバーシティの教科書: 多様性尊重社会へのキーワード",
  "Price": 1980,
  "Category": "ジャンル別",
  "Points": 20
 },
 {
  "Asin": "4756254209",
  "URL": "https://www.amazon.co.jp/dp/4756254209?tag=99hatena-22&linkCode=ogi&th=1&psc=1",
  "ImageURL": "なし",
  "Publisher": "パイインターナショナル",
  "Contributor": "井上 浩輝(著)",
  "Booktype": "単行本（ソフトカバー）",
  "Title": "Romantic Forest おとぎの森の動物たち",
  "Price": 1760,
  "Category": "写真家",
  "Points": 18
 },
 {
  "Asin": "4760828486",
  "URL": "https://www.amazon.co.jp/dp/4760828486?tag=99hatena-22&linkCode=ogi&th=1&psc=1",
  "ImageURL": "なし",
  "Publisher": "金子書房",
  "Contributor": "キャロル・ストック・クラノウィッツ(著)",
  "Booktype": "単行本",
  "Title": "でこぼこした発達の子どもたち: 感覚統合の問題と上手につきあっていくために",
  "Price": 4400,
  "Category": "ジャンル別",
  "Points": 44
 },
 {
  "Asin": "4866751312",
  "URL": "https://www.amazon.co.jp/dp/4866751312?tag=99hatena-22&linkCode=ogi&th=1&psc=1",
  "ImageURL": "なし",
  "Publisher": "フレックスコミックス",
  "Contributor": "ユキヲ(著)",
  "Booktype": "コミック",
  "Title": "邪神ちゃんドロップキック (16) (メテオCOMICS)",
  "Price": 660,
  "Category": "コミック",
  "Points": 7
 },
 {
  "Asin": "458262071X",
  "URL": "https://www.amazon.co.jp/dp/458262071X?tag=99hatena-22&linkCode=ogi&th=1&psc=1",
  "ImageURL": "https://m.media-amazon.com/images/I/418FZxw7QJL.jpg",
  "Publisher": "平凡社",
  "Contributor": "小池 一子(著)",
  "Booktype": "単行本",
  "Title": "美術/中間子 小池一子の現場",
  "Price": 3300,
  "Category": "ジャンル別",
  "Points": 60
 },
 {
  "Asin": "4866751304",
  "URL": "https://www.amazon.co.jp/dp/4866751304?tag=99hatena-22&linkCode=ogi&th=1&psc=1",
  "ImageURL": "なし",
  "Publisher": "フレックスコミックス",
  "Contributor": "藤原里(著)",
  "Booktype": "コミック",
  "Title": "小西先生、進捗いかがですか? (1) (メテオCOMICS)",
  "Price": 693,
  "Category": "コミック",
  "Points": 7
 },
 {
  "Asin": "4815608083",
  "URL": "https://www.amazon.co.jp/dp/4815608083?tag=99hatena-22&linkCode=ogi&th=1&psc=1",
  "ImageURL": "https://m.media-amazon.com/images/I/41xkDEjWgzL.jpg",
  "Publisher": "SBクリエイティブ",
  "Contributor": "平坂読(著)",
  "Booktype": "文庫",
  "Title": "〆切前には百合が捗る (GA文庫)",
  "Price": 770,
  "Category": "ライトノベル,Featured Categories",
  "Points": 8
 },
 {
  "Asin": "4815607621",
  "URL": "https://www.amazon.co.jp/dp/4815607621?tag=99hatena-22&linkCode=ogi&th=1&psc=1",
  "ImageURL": "https://m.media-amazon.com/images/I/41p5G7EO6yL.jpg",
  "Publisher": "SBクリエイティブ",
  "Contributor": "　(著)",
  "Booktype": "単行本",
  "Title": "1日1ページ イラストで身につく 科学の教養365",
  "Price": 2200,
  "Category": "科学読み物",
  "Points": 40
 },
 {
  "Asin": "4815607974",
  "URL": "https://www.amazon.co.jp/dp/4815607974?tag=99hatena-22&linkCode=ogi&th=1&psc=1",
  "ImageURL": "https://m.media-amazon.com/images/I/41BciduS3-L.jpg",
  "Publisher": "SBクリエイティブ",
  "Contributor": "白石定規(著)",
  "Booktype": "単行本",
  "Title": "魔女の旅々15 (GAノベル)",
  "Price": 1320,
  "Category": "ライトノベル,Featured Categories",
  "Points": 24
 },
 {
  "Asin": "4041098351",
  "URL": "https://www.amazon.co.jp/dp/4041098351?tag=99hatena-22&linkCode=ogi&th=1&psc=1",
  "ImageURL": "なし",
  "Publisher": "KADOKAWA",
  "Contributor": "Little Rooms(著)",
  "Booktype": "単行本",
  "Title": "狭い部屋で広く暮らす",
  "Price": 1430,
  "Category": "ノンフィクション",
  "Points": 14
 },
 {
  "Asin": "4780424097",
  "URL": "https://www.amazon.co.jp/dp/4780424097?tag=99hatena-22&linkCode=ogi&th=1&psc=1",
  "ImageURL": "なし",
  "Publisher": "メイツ出版",
  "Contributor": "未定(著)",
  "Booktype": "単行本（ソフトカバー）",
  "Title": "みんなが知りたい! 「世界の大発見」がわかる本 改訂版 (まなぶっく)",
  "Price": 1826,
  "Category": "社会・くらし",
  "Points": 18
 },
 {
  "Asin": "4876153655",
  "URL": "https://www.amazon.co.jp/dp/4876153655?tag=99hatena-22&linkCode=ogi&th=1&psc=1",
  "ImageURL": "なし",
  "Publisher": "語研",
  "Contributor": "ローラ・クロネル(著)",
  "Booktype": "単行本",
  "Title": "感情と気持ちを伝える! 英会話フレーズブック",
  "Price": 1760,
  "Category": "ジャンル別",
  "Points": 18
 },
 {
  "Asin": "4756921221",
  "URL": "https://www.amazon.co.jp/dp/4756921221?tag=99hatena-22&linkCode=ogi&th=1&psc=1",
  "ImageURL": "なし",
  "Publisher": "明日香出版社",
  "Contributor": "菅原 大介(著)",
  "Booktype": "単行本（ソフトカバー）",
  "Title": "新・箇条書き思考",
  "Price": 1760,
  "Category": "仕事術・整理法",
  "Points": 32
 },
 {
  "Asin": "4756921213",
  "URL": "https://www.amazon.co.jp/dp/4756921213?tag=99hatena-22&linkCode=ogi&th=1&psc=1",
  "ImageURL": "なし",
  "Publisher": "明日香出版社",
  "Contributor": "相原 秀哉(著)",
  "Booktype": "単行本（ソフトカバー）",
  "Title": "リモートワーク段取り仕事術",
  "Price": 1650,
  "Category": "仕事術・整理法",
  "Points": 17
 },
 {
  "Asin": "4295010391",
  "URL": "https://www.amazon.co.jp/dp/4295010391?tag=99hatena-22&linkCode=ogi&th=1&psc=1",
  "ImageURL": "なし",
  "Publisher": "インプレス",
  "Contributor": "間久保 恭子(著)",
  "Booktype": "単行本（ソフトカバー）",
  "Title": "かんたん合格 ITパスポート過去問題集 令和3年度 春期 (かんたん合格シリーズ)",
  "Price": 1298,
  "Category": "ITパスポート",
  "Points": 13
 },
 {
  "Asin": "4295010405",
  "URL": "https://www.amazon.co.jp/dp/4295010405?tag=99hatena-22&linkCode=ogi&th=1&psc=1",
  "ImageURL": "なし",
  "Publisher": "インプレス",
  "Contributor": "長谷川 秀樹(著)",
  "Booktype": "単行本（ソフトカバー）",
  "Title": "Slack デジタルシフト リーダー10人に学ぶ、激動の時代に成長できるワークスタイル変革 (できるビジネス)",
  "Price": 1650,
  "Category": "人事・労務管理",
  "Points": 17
 },
 {
  "Asin": "4904076788",
  "URL": "https://www.amazon.co.jp/dp/4904076788?tag=99hatena-22&linkCode=ogi&th=1&psc=1",
  "ImageURL": "なし",
  "Publisher": "文踊社",
  "Contributor": "沢村慎太朗(著)",
  "Booktype": "単行本",
  "Title": "午前零時の自動車評論18",
  "Price": 1650,
  "Category": "車・バイク",
  "Points": 17
 },
 {
  "Asin": "4576201972",
  "URL": "https://www.amazon.co.jp/dp/4576201972?tag=99hatena-22&linkCode=ogi&th=1&psc=1",
  "ImageURL": "https://m.media-amazon.com/images/I/41J83JicgdL.jpg",
  "Publisher": "マドンナメイト社",
  "Contributor": "素人投稿編集部(編集)",
  "Booktype": "文庫",
  "Title": "素人投稿スペシャル 熟年回春(仮) (マドンナメイト文庫)",
  "Price": 776,
  "Category": "ジャンル別,Featured Categories",
  "Points": 8
 },
 {
  "Asin": "4576201948",
  "URL": "https://www.amazon.co.jp/dp/4576201948?tag=99hatena-22&linkCode=ogi&th=1&psc=1",
  "ImageURL": "https://m.media-amazon.com/images/I/41J83JicgdL.jpg",
  "Publisher": "マドンナメイト社",
  "Contributor": "浦路 直彦(著)",
  "Booktype": "文庫",
  "Title": "義母の熟乳、叔母の桃尻 ダブル相姦ハーレム(仮) (マドンナメイト文庫)",
  "Price": 776,
  "Category": "ジャンル別,Featured Categories",
  "Points": 8
 },
 {
  "Asin": "4596978964",
  "URL": "https://www.amazon.co.jp/dp/4596978964?tag=99hatena-22&linkCode=ogi&th=1&psc=1",
  "ImageURL": "https://m.media-amazon.com/images/I/515mocRAcNL.jpg",
  "Publisher": "ハーパーコリンズ・ジャパン",
  "Contributor": "しのざき 薫(著)",
  "Booktype": "コミック",
  "Title": "湖の秘密",
  "Price": 660,
  "Category": "コミック",
  "Points": 7
 },
 {
  "Asin": "459697893X",
  "URL": "https://www.amazon.co.jp/dp/459697893X?tag=99hatena-22&linkCode=ogi&th=1&psc=1",
  "ImageURL": "https://m.media-amazon.com/images/I/510i4kTjX6L.jpg",
  "Publisher": "ハーパーコリンズ・ジャパン",
  "Contributor": "一重夕子(著)",
  "Booktype": "コミック",
  "Title": "誘惑を望んだ夜",
  "Price": 660,
  "Category": "コミック",
  "Points": 7
 },
 {
  "Asin": "4596978905",
  "URL": "https://www.amazon.co.jp/dp/4596978905?tag=99hatena-22&linkCode=ogi&th=1&psc=1",
  "ImageURL": "https://m.media-amazon.com/images/I/51ItD3h6F3L.jpg",
  "Publisher": "ハーパーコリンズ・ジャパン",
  "Contributor": "藤田和子(著)",
  "Booktype": "コミック",
  "Title": "地上より永遠へ",
  "Price": 681,
  "Category": "コミック",
  "Points": 7
 },
 {
  "Asin": "4576201964",
  "URL": "https://www.amazon.co.jp/dp/4576201964?tag=99hatena-22&linkCode=ogi&th=1&psc=1",
  "ImageURL": "https://m.media-amazon.com/images/I/41J83JicgdL.jpg",
  "Publisher": "マドンナメイト社",
  "Contributor": "美里 ユウキ(著)",
  "Booktype": "文庫",
  "Title": "JKももいろ遊戯(仮) (マドンナメイト文庫)",
  "Price": 776,
  "Category": "ジャンル別,Featured Categories",
  "Points": 8
 },
 {
  "Asin": "4832272330",
  "URL": "https://www.amazon.co.jp/dp/4832272330?tag=99hatena-22&linkCode=ogi&th=1&psc=1",
  "ImageURL": "なし",
  "Publisher": "芳文社",
  "Contributor": "牛木義隆(著)",
  "Booktype": "コミック",
  "Title": "夢喰いメリー 24 (まんがタイムKRコミックス)",
  "Price": 693,
  "Category": "コミック",
  "Points": 7
 },
 {
  "Asin": "4098608294",
  "URL": "https://www.amazon.co.jp/dp/4098608294?tag=99hatena-22&linkCode=ogi&th=1&psc=1",
  "ImageURL": "なし",
  "Publisher": "小学館",
  "Contributor": "ゆうき まさみ(著)",
  "Booktype": "コミック",
  "Title": "新九郎、奔る! (6)",
  "Price": 693,
  "Category": "コミック",
  "Points": 7
 },
 {
  "Asin": "4596978913",
  "URL": "https://www.amazon.co.jp/dp/4596978913?tag=99hatena-22&linkCode=ogi&th=1&psc=1",
  "ImageURL": "https://m.media-amazon.com/images/I/51A5l3OrseL.jpg",
  "Publisher": "ハーパーコリンズ・ジャパン",
  "Contributor": "松尾しより(著)",
  "Booktype": "コミック",
  "Title": "古城が呼ぶ愛",
  "Price": 660,
  "Category": "コミック",
  "Points": 7
 },
 {
  "Asin": "457620193X",
  "URL": "https://www.amazon.co.jp/dp/457620193X?tag=99hatena-22&linkCode=ogi&th=1&psc=1",
  "ImageURL": "https://m.media-amazon.com/images/I/417obDwMUBL.jpg",
  "Publisher": "二見書房",
  "Contributor": "木野 美森(著)",
  "Booktype": "文庫",
  "Title": "後宮護衛の偽妃ですが、陛下に愛されて困っています! (ハニー文庫, ハニーブンコ)",
  "Price": 784,
  "Category": "ライトノベル,Featured Categories",
  "Points": 8
 },
 {
  "Asin": "4576201956",
  "URL": "https://www.amazon.co.jp/dp/4576201956?tag=99hatena-22&linkCode=ogi&th=1&psc=1",
  "ImageURL": "https://m.media-amazon.com/images/I/41J83JicgdL.jpg",
  "Publisher": "マドンナメイト社",
  "Contributor": "哀澤 渚(著)",
  "Booktype": "文庫",
  "Title": "甘い生活 居候の処女妹(仮) (マドンナメイト文庫)",
  "Price": 776,
  "Category": "ジャンル別,Featured Categories",
  "Points": 8
 },
 {
  "Asin": "4832272349",
  "URL": "https://www.amazon.co.jp/dp/4832272349?tag=99hatena-22&linkCode=ogi&th=1&psc=1",
  "ImageURL": "なし",
  "Publisher": "芳文社",
  "Contributor": "火曜(著)",
  "Booktype": "コミック",
  "Title": "ちょっといっぱい! 7 (まんがタイムKRコミックス)",
  "Price": 693,
  "Category": "コミック",
  "Points": 7
 },
 {
  "Asin": "4596978921",
  "URL": "https://www.amazon.co.jp/dp/4596978921?tag=99hatena-22&linkCode=ogi&th=1&psc=1",
  "ImageURL": "https://m.media-amazon.com/images/I/51+QvSFwoxL.jpg",
  "Publisher": "ハーパーコリンズ・ジャパン",
  "Contributor": "松尾しより(著)",
  "Booktype": "コミック",
  "Title": "大富豪と愛を語る花",
  "Price": 660,
  "Category": "コミック",
  "Points": 7
 },
 {
  "Asin": "4596978956",
  "URL": "https://www.amazon.co.jp/dp/4596978956?tag=99hatena-22&linkCode=ogi&th=1&psc=1",
  "ImageURL": "https://m.media-amazon.com/images/I/5120BON3BnL.jpg",
  "Publisher": "ハーパーコリンズ・ジャパン",
  "Contributor": "瑚白ゆう(著)",
  "Booktype": "コミック",
  "Title": "すれ違いのクリスマス",
  "Price": 660,
  "Category": "コミック",
  "Points": 7
 },
 {
  "Asin": "4596978948",
  "URL": "https://www.amazon.co.jp/dp/4596978948?tag=99hatena-22&linkCode=ogi&th=1&psc=1",
  "ImageURL": "https://m.media-amazon.com/images/I/51SuVvyoPnL.jpg",
  "Publisher": "ハーパーコリンズ・ジャパン",
  "Contributor": "桐坂真生(著)",
  "Booktype": "コミック",
  "Title": "囚われの宝石",
  "Price": 660,
  "Category": "コミック",
  "Points": 7
 },
 {
  "Asin": "4098503085",
  "URL": "https://www.amazon.co.jp/dp/4098503085?tag=99hatena-22&linkCode=ogi&th=1&psc=1",
  "ImageURL": "なし",
  "Publisher": "小学館",
  "Contributor": "七月 鏡一(原著)",
  "Booktype": "コミック",
  "Title": "ギジン (3)",
  "Price": 660,
  "Category": "コミック",
  "Points": 7
 },
 {
  "Asin": "4832272357",
  "URL": "https://www.amazon.co.jp/dp/4832272357?tag=99hatena-22&linkCode=ogi&th=1&psc=1",
  "ImageURL": "なし",
  "Publisher": "芳文社",
  "Contributor": "きららファンタジア製作委員会(企画・原案)",
  "Booktype": "コミック",
  "Title": "きららファンタジアイラストレーションズ 1 (まんがタイムKRコミックス)",
  "Price": 4950,
  "Category": "コミック",
  "Points": 50
 },
 {
  "Asin": "4046047313",
  "URL": "https://www.amazon.co.jp/dp/4046047313?tag=99hatena-22&linkCode=ogi&th=1&psc=1",
  "ImageURL": "なし",
  "Publisher": "KADOKAWA",
  "Contributor": "齋藤 孝(著)",
  "Booktype": "単行本",
  "Title": "小学3年生から始める!こども知識力1200 学習意欲が育ち、頭がドンドンよくなる",
  "Price": 1760,
  "Category": "小学教科書・参考書",
  "Points": 18
 },
 {
  "Asin": "4803014728",
  "URL": "https://www.amazon.co.jp/dp/4803014728?tag=99hatena-22&linkCode=ogi&th=1&psc=1",
  "ImageURL": "なし",
  "Publisher": "アース・スターエンターテイメント",
  "Contributor": "犬丸(著)",
  "Booktype": "コミック",
  "Title": "私の従僕 俺の主人はあくまで天使な公爵令嬢 (1) (アース・スターコミックス)",
  "Price": 660,
  "Category": "コミック",
  "Points": 7
 },
 {
  "Asin": "480301471X",
  "URL": "https://www.amazon.co.jp/dp/480301471X?tag=99hatena-22&linkCode=ogi&th=1&psc=1",
  "ImageURL": "なし",
  "Publisher": "アース・スターエンターテイメント",
  "Contributor": "となりける(著)",
  "Booktype": "コミック",
  "Title": "願いを叶えてもらおうと悪魔を召喚したけど、可愛かったので結婚しました ~悪魔の新妻~ (1) (アース・スターコミックス)",
  "Price": 660,
  "Category": "コミック",
  "Points": 7
 },
 {
  "Asin": "4803014744",
  "URL": "https://www.amazon.co.jp/dp/4803014744?tag=99hatena-22&linkCode=ogi&th=1&psc=1",
  "ImageURL": "なし",
  "Publisher": "アース・スターエンターテイメント",
  "Contributor": "納都花丸(著)",
  "Booktype": "コミック",
  "Title": "即死チートが最強すぎて、異世界のやつらがまるで相手にならないんですが。-ΑΩ- (5) (アース・スターコミックス)",
  "Price": 660,
  "Category": "コミック",
  "Points": 7
 },
 {
  "Asin": "4803014736",
  "URL": "https://www.amazon.co.jp/dp/4803014736?tag=99hatena-22&linkCode=ogi&th=1&psc=1",
  "ImageURL": "なし",
  "Publisher": "アース・スターエンターテイメント",
  "Contributor": "ユンボ(著)",
  "Booktype": "コミック",
  "Title": "領民0人スタートの辺境領主様 ~青のディアスと蒼角の乙女~ (4) (アース・スターコミックス)",
  "Price": 660,
  "Category": "コミック",
  "Points": 7
 },
 {
  "Asin": "4866574046",
  "URL": "https://www.amazon.co.jp/dp/4866574046?tag=99hatena-22&linkCode=ogi&th=1&psc=1",
  "ImageURL": "なし",
  "Publisher": "フロンティアワークス",
  "Contributor": "夜愁 とーや(著)",
  "Booktype": "コミック",
  "Title": "観賞対象から告白されました。 3 (アリアンローズコミックス)",
  "Price": 748,
  "Category": "コミック",
  "Points": 7
 },
 {
  "Asin": "4866574062",
  "URL": "https://www.amazon.co.jp/dp/4866574062?tag=99hatena-22&linkCode=ogi&th=1&psc=1",
  "ImageURL": "なし",
  "Publisher": "フロンティアワークス",
  "Contributor": "森本 あき(著)",
  "Booktype": "文庫",
  "Title": "世界でたったひとりの生意気な花嫁 (ダリア文庫)",
  "Price": 750,
  "Category": "ボーイズラブノベルス,Featured Categories",
  "Points": 8
 },
 {
  "Asin": "4866573880",
  "URL": "https://www.amazon.co.jp/dp/4866573880?tag=99hatena-22&linkCode=ogi&th=1&psc=1",
  "ImageURL": "なし",
  "Publisher": "フロンティアワークス",
  "Contributor": "遊森 謡子(著)",
  "Booktype": "単行本（ソフトカバー）",
  "Title": "薬草茶を作ります ~お腹がすいたらスープもどうぞ~ 3 (アリアンローズ)",
  "Price": 1540,
  "Category": "ライトノベル,Featured Categories",
  "Points": 15
 },
 {
  "Asin": "4098607816",
  "URL": "https://www.amazon.co.jp/dp/4098607816?tag=99hatena-22&linkCode=ogi&th=1&psc=1",
  "ImageURL": "なし",
  "Publisher": "小学館",
  "Contributor": "オジロ マコト(著)",
  "Booktype": "コミック",
  "Title": "君は放課後インソムニア (5)",
  "Price": 650,
  "Category": "コミック",
  "Points": 7
 },
 {
  "Asin": "4866573910",
  "URL": "https://www.amazon.co.jp/dp/4866573910?tag=99hatena-22&linkCode=ogi&th=1&psc=1",
  "ImageURL": "なし",
  "Publisher": "フロンティアワークス",
  "Contributor": "佐槻 奏多(著)",
  "Booktype": "単行本（ソフトカバー）",
  "Title": "どうも、悪役にされた令嬢ですけれど 2 (アリアンローズ)",
  "Price": 1430,
  "Category": "ライトノベル,Featured Categories",
  "Points": 14
 },
 {
  "Asin": "4758083576",
  "URL": "https://www.amazon.co.jp/dp/4758083576?tag=99hatena-22&linkCode=ogi&th=1&psc=1",
  "ImageURL": "なし",
  "Publisher": "一迅社",
  "Contributor": "ホリ(著)",
  "Booktype": "コミック",
  "Title": "アズールレーン びそくぜんしんっ! (2) 特装版 (4コマKINGSぱれっとコミックス)",
  "Price": 4620,
  "Category": "コミック",
  "Points": 46
 },
 {
  "Asin": "4758083568",
  "URL": "https://www.amazon.co.jp/dp/4758083568?tag=99hatena-22&linkCode=ogi&th=1&psc=1",
  "ImageURL": "なし",
  "Publisher": "一迅社",
  "Contributor": "ホリ(著)",
  "Booktype": "コミック",
  "Title": "アズールレーン びそくぜんしんっ! (2) (4コマKINGSぱれっとコミックス)",
  "Price": 880,
  "Category": "コミック",
  "Points": 9
 },
 {
  "Asin": "4757570023",
  "URL": "https://www.amazon.co.jp/dp/4757570023?tag=99hatena-22&linkCode=ogi&th=1&psc=1",
  "ImageURL": "なし",
  "Publisher": "スクウェア・エニックス",
  "Contributor": "サトウとシオ(著)",
  "Booktype": "コミック",
  "Title": "たとえばラストダンジョン前の村の少年が序盤の街の食堂で働く日常物語(1) (GC)",
  "Price": 660,
  "Category": "コミック",
  "Points": 7
 },
 {
  "Asin": "4815607575",
  "URL": "https://www.amazon.co.jp/dp/4815607575?tag=99hatena-22&linkCode=ogi&th=1&psc=1",
  "ImageURL": "https://m.media-amazon.com/images/I/51Pg6cmovML.jpg",
  "Publisher": "SBクリエイティブ",
  "Contributor": "三木 なずな(著)",
  "Booktype": "単行本",
  "Title": "貴族転生4 ~恵まれた生まれから最強の力を得る~ (GAノベル)",
  "Price": 1320,
  "Category": "ライトノベル,Featured Categories",
  "Points": 13
 },
 {
  "Asin": "475757004X",
  "URL": "https://www.amazon.co.jp/dp/475757004X?tag=99hatena-22&linkCode=ogi&th=1&psc=1",
  "ImageURL": "https://m.media-amazon.com/images/I/51C8p3HwH9L.jpg",
  "Publisher": "スクウェア・エニックス",
  "Contributor": "天野ハザマ(著)",
  "Booktype": "コミック",
  "Title": "金貨1枚で変わる冒険者生活(2) (GCO)",
  "Price": 660,
  "Category": "コミック",
  "Points": 7
 },
 {
  "Asin": "4757570007",
  "URL": "https://www.amazon.co.jp/dp/4757570007?tag=99hatena-22&linkCode=ogi&th=1&psc=1",
  "ImageURL": "なし",
  "Publisher": "スクウェア・エニックス",
  "Contributor": "宮澤伊織(著)",
  "Booktype": "コミック",
  "Title": "裏世界ピクニック(5) (GC)",
  "Price": 660,
  "Category": "コミック",
  "Points": 7
 },
 {
  "Asin": "475756998X",
  "URL": "https://www.amazon.co.jp/dp/475756998X?tag=99hatena-22&linkCode=ogi&th=1&psc=1",
  "ImageURL": "なし",
  "Publisher": "スクウェア・エニックス",
  "Contributor": "進行諸島(著)",
  "Booktype": "コミック",
  "Title": "殲滅魔導の最強賢者 無才の賢者、魔導を極め最強へ至る(1) (GCUP!)",
  "Price": 660,
  "Category": "コミック",
  "Points": 7
 },
 {
  "Asin": "4831862622",
  "URL": "https://www.amazon.co.jp/dp/4831862622?tag=99hatena-22&linkCode=ogi&th=1&psc=1",
  "ImageURL": "https://m.media-amazon.com/images/I/518kEuZya0L.jpg",
  "Publisher": "法藏館",
  "Contributor": "竹貫 元勝(著)",
  "Booktype": "単行本",
  "Title": "隠元と黄檗宗の歴史",
  "Price": 3850,
  "Category": "ジャンル別",
  "Points": 39
 },
 {
  "Asin": "4757570015",
  "URL": "https://www.amazon.co.jp/dp/4757570015?tag=99hatena-22&linkCode=ogi&th=1&psc=1",
  "ImageURL": "なし",
  "Publisher": "スクウェア・エニックス",
  "Contributor": "月夜涙(著)",
  "Booktype": "コミック",
  "Title": "スライム転生。大賢者が養女エルフに抱きしめられてます(5) (GC)",
  "Price": 660,
  "Category": "コミック",
  "Points": 7
 },
 {
  "Asin": "4815607583",
  "URL": "https://www.amazon.co.jp/dp/4815607583?tag=99hatena-22&linkCode=ogi&th=1&psc=1",
  "ImageURL": "https://m.media-amazon.com/images/I/51QYJv+42vL.jpg",
  "Publisher": "SBクリエイティブ",
  "Contributor": "ケンノジ(著)",
  "Booktype": "文庫",
  "Title": "痴漢されそうになっているS級美少女を助けたら隣の席の幼馴染だった3 (GA文庫)",
  "Price": 704,
  "Category": "ライトノベル,Featured Categories",
  "Points": 7
 },
 {
  "Asin": "4199507272",
  "URL": "https://www.amazon.co.jp/dp/4199507272?tag=99hatena-22&linkCode=ogi&th=1&psc=1",
  "ImageURL": "なし",
  "Publisher": "徳間書店",
  "Contributor": "羽浪由惚(著)",
  "Booktype": "コミック",
  "Title": "夜のナイチンゲール 2 (リュウコミックス)",
  "Price": 990,
  "Category": "コミック",
  "Points": 10
 },
 {
  "Asin": "4757570066",
  "URL": "https://www.amazon.co.jp/dp/4757570066?tag=99hatena-22&linkCode=ogi&th=1&psc=1",
  "ImageURL": "なし",
  "Publisher": "スクウェア・エニックス",
  "Contributor": "山内泰延(著)",
  "Booktype": "コミック",
  "Title": "白雷の騎士(2) (GCO)",
  "Price": 660,
  "Category": "コミック",
  "Points": 7
 },
 {
  "Asin": "4757570031",
  "URL": "https://www.amazon.co.jp/dp/4757570031?tag=99hatena-22&linkCode=ogi&th=1&psc=1",
  "ImageURL": "なし",
  "Publisher": "スクウェア・エニックス",
  "Contributor": "サトウとシオ(著)",
  "Booktype": "コミック",
  "Title": "たとえばラストダンジョン前の村の少年が序盤の街で暮らすような物語(7) (GCO)",
  "Price": 660,
  "Category": "コミック",
  "Points": 7
 },
 {
  "Asin": "4757570058",
  "URL": "https://www.amazon.co.jp/dp/4757570058?tag=99hatena-22&linkCode=ogi&th=1&psc=1",
  "ImageURL": "https://m.media-amazon.com/images/I/51vIHCr43fL.jpg",
  "Publisher": "スクウェア・エニックス",
  "Contributor": "木崎アオコ(著)",
  "Booktype": "コミック",
  "Title": "グラスフィート(2) (GCO)",
  "Price": 660,
  "Category": "コミック",
  "Points": 7
 },
 {
  "Asin": "4757569963",
  "URL": "https://www.amazon.co.jp/dp/4757569963?tag=99hatena-22&linkCode=ogi&th=1&psc=1",
  "ImageURL": "なし",
  "Publisher": "スクウェア・エニックス",
  "Contributor": "進行諸島(著)",
  "Booktype": "コミック",
  "Title": "失格紋の最強賢者 ~世界最強の賢者が更に強くなるために転生しました~(13) (GCUP!)",
  "Price": 660,
  "Category": "コミック",
  "Points": 7
 },
 {
  "Asin": "4774331678",
  "URL": "https://www.amazon.co.jp/dp/4774331678?tag=99hatena-22&linkCode=ogi&th=1&psc=1",
  "ImageURL": "なし",
  "Publisher": "くもん出版",
  "Contributor": "森有子(イラスト)",
  "Booktype": "単行本（ソフトカバー）",
  "Title": "古事記",
  "Price": 880,
  "Category": "コミック",
  "Points": 9
 },
 {
  "Asin": "4047364584",
  "URL": "https://www.amazon.co.jp/dp/4047364584?tag=99hatena-22&linkCode=ogi&th=1&psc=1",
  "ImageURL": "なし",
  "Publisher": "KADOKAWA",
  "Contributor": "十日 草輔(著)",
  "Booktype": "コミック",
  "Title": "王様ランキング 9 (ビームコミックス)",
  "Price": 759,
  "Category": "コミック",
  "Points": 8
 },
 {
  "Asin": "4098503433",
  "URL": "https://www.amazon.co.jp/dp/4098503433?tag=99hatena-22&linkCode=ogi&th=1&psc=1",
  "ImageURL": "なし",
  "Publisher": "小学館",
  "Contributor": "ゆきの(著)",
  "Booktype": "コミック",
  "Title": "1/10の花嫁 (4)",
  "Price": 650,
  "Category": "コミック",
  "Points": 7
 },
 {
  "Asin": "4091793185",
  "URL": "https://www.amazon.co.jp/dp/4091793185?tag=99hatena-22&linkCode=ogi&th=1&psc=1",
  "ImageURL": "なし",
  "Publisher": "小学館",
  "Contributor": "ゆうき まさみ(著)",
  "Booktype": "単行本",
  "Title": "愛蔵版機動警察パトレイバー (13)",
  "Price": 1980,
  "Category": "コミック",
  "Points": 20
 },
 {
  "Asin": "4098503476",
  "URL": "https://www.amazon.co.jp/dp/4098503476?tag=99hatena-22&linkCode=ogi&th=1&psc=1",
  "ImageURL": "なし",
  "Publisher": "小学館",
  "Contributor": "モリ タイシ(著)",
  "Booktype": "コミック",
  "Title": "あそこではたらくムスブさん (3)",
  "Price": 650,
  "Category": "コミック",
  "Points": 7
 },
 {
  "Asin": "4047364592",
  "URL": "https://www.amazon.co.jp/dp/4047364592?tag=99hatena-22&linkCode=ogi&th=1&psc=1",
  "ImageURL": "なし",
  "Publisher": "KADOKAWA",
  "Contributor": "丸尾 末広(著)",
  "Booktype": "コミック",
  "Title": "天國 パライゾ (ビームコミックス)",
  "Price": 1012,
  "Category": "コミック",
  "Points": 10
 },
 {
  "Asin": "4864729867",
  "URL": "https://www.amazon.co.jp/dp/4864729867?tag=99hatena-22&linkCode=ogi&th=1&psc=1",
  "ImageURL": "なし",
  "Publisher": "TOブックス",
  "Contributor": "gap collection 編集部(著)",
  "Booktype": "大型本",
  "Title": "2021 S/S gap PRESS vol.157 PARIS/LONDON (gap PRESS Collections)",
  "Price": 1870,
  "Category": "ジャンル別",
  "Points": 34
 },
 {
  "Asin": "4823601165",
  "URL": "https://www.amazon.co.jp/dp/4823601165?tag=99hatena-22&linkCode=ogi&th=1&psc=1",
  "ImageURL": "なし",
  "Publisher": "ジーオーティー",
  "Contributor": "ほよよ(著)",
  "Booktype": "コミック",
  "Title": "こら!あんた母親を口説いて何しようっていうの!",
  "Price": 1760,
  "Category": "コミック",
  "Points": 18
 },
 {
  "Asin": "4333028388",
  "URL": "https://www.amazon.co.jp/dp/4333028388?tag=99hatena-22&linkCode=ogi&th=1&psc=1",
  "ImageURL": "https://m.media-amazon.com/images/I/51O+HFiCuNL.jpg",
  "Publisher": "佼成出版社",
  "Contributor": "中川ひろたか(著)",
  "Booktype": "単行本（ソフトカバー）",
  "Title": "おとのさま、まほうつかいになる",
  "Price": 1320,
  "Category": "ジャンル別",
  "Points": 13
 },
 {
  "Asin": "4295010456",
  "URL": "https://www.amazon.co.jp/dp/4295010456?tag=99hatena-22&linkCode=ogi&th=1&psc=1",
  "ImageURL": "なし",
  "Publisher": "インプレス",
  "Contributor": "髙橋 慈子(著)",
  "Booktype": "単行本（ソフトカバー）",
  "Title": "速効メソッド ITエンジニアのためのビジネス文書作成術",
  "Price": 2420,
  "Category": "ビジネス文書",
  "Points": 44
 },
 {
  "Asin": "4098608332",
  "URL": "https://www.amazon.co.jp/dp/4098608332?tag=99hatena-22&linkCode=ogi&th=1&psc=1",
  "ImageURL": "なし",
  "Publisher": "小学館",
  "Contributor": "山崎 コータ(著)",
  "Booktype": "コミック",
  "Title": "ぼくは黒蜜さんの腹筋がこわい (2)",
  "Price": 693,
  "Category": "コミック",
  "Points": 7
 },
 {
  "Asin": "4831862975",
  "URL": "https://www.amazon.co.jp/dp/4831862975?tag=99hatena-22&linkCode=ogi&th=1&psc=1",
  "ImageURL": "https://m.media-amazon.com/images/I/31tqhRVKQLL.jpg",
  "Publisher": "法藏館",
  "Contributor": "赤田 光男(著)",
  "Booktype": "単行本",
  "Title": "中世都市の歳時記と宗教民俗",
  "Price": 11000,
  "Category": "ジャンル別",
  "Points": 110
 },
 {
  "Asin": "4502366714",
  "URL": "https://www.amazon.co.jp/dp/4502366714?tag=99hatena-22&linkCode=ogi&th=1&psc=1",
  "ImageURL": "なし",
  "Publisher": "中央経済社",
  "Contributor": "竹内 朗(編集)",
  "Booktype": "単行本",
  "Title": "図解 不祥事の社内調査がわかる本",
  "Price": 2750,
  "Category": "ジャンル別",
  "Points": 28
 },
 {
  "Asin": "449104287X",
  "URL": "https://www.amazon.co.jp/dp/449104287X?tag=99hatena-22&linkCode=ogi&th=1&psc=1",
  "ImageURL": "https://m.media-amazon.com/images/I/51CUmvdGT7L.jpg",
  "Publisher": "東洋館出版社",
  "Contributor": "理科おもしろゼミ(著)",
  "Booktype": "単行本",
  "Title": "ベストな展開が選べる! 小学校理科「フローチャート型」授業ガイド",
  "Price": 2200,
  "Category": "理科",
  "Points": 40
 },
 {
  "Asin": "4760824367",
  "URL": "https://www.amazon.co.jp/dp/4760824367?tag=99hatena-22&linkCode=ogi&th=1&psc=1",
  "ImageURL": "なし",
  "Publisher": "金子書房",
  "Contributor": "二村英幸(著)",
  "Booktype": "単行本",
  "Title": "キャリア自律を育む心理測定ツールの開発と実践: 大学教育における新展開",
  "Price": 4290,
  "Category": "ジャンル別",
  "Points": 43
 },
 {
  "Asin": "4831877085",
  "URL": "https://www.amazon.co.jp/dp/4831877085?tag=99hatena-22&linkCode=ogi&th=1&psc=1",
  "ImageURL": "なし",
  "Publisher": "法藏館",
  "Contributor": "京都仏教各宗学校連合会(編集)",
  "Booktype": "単行本",
  "Title": "新編 大蔵経: 成立と変遷",
  "Price": 1980,
  "Category": "ジャンル別",
  "Points": 20
 },
 {
  "Asin": "4098503468",
  "URL": "https://www.amazon.co.jp/dp/4098503468?tag=99hatena-22&linkCode=ogi&th=1&psc=1",
  "ImageURL": "なし",
  "Publisher": "小学館",
  "Contributor": "瀬戸 ミクモ(著)",
  "Booktype": "コミック",
  "Title": "ボンバボーイ (4)",
  "Price": 650,
  "Category": "コミック",
  "Points": 7
 },
 {
  "Asin": "4831877360",
  "URL": "https://www.amazon.co.jp/dp/4831877360?tag=99hatena-22&linkCode=ogi&th=1&psc=1",
  "ImageURL": "https://m.media-amazon.com/images/I/51HqDVMzkWL.jpg",
  "Publisher": "法藏館",
  "Contributor": "谷口 匡(著)",
  "Booktype": "単行本",
  "Title": "西遊詩巻: 頼山陽の九州漫遊",
  "Price": 2750,
  "Category": "ジャンル別",
  "Points": 28
 },
 {
  "Asin": "4098608308",
  "URL": "https://www.amazon.co.jp/dp/4098608308?tag=99hatena-22&linkCode=ogi&th=1&psc=1",
  "ImageURL": "なし",
  "Publisher": "小学館",
  "Contributor": "中川 いさみ(著)",
  "Booktype": "コミック",
  "Title": "DIYマン",
  "Price": 900,
  "Category": "コミック",
  "Points": 9
 },
 {
  "Asin": "4839974713",
  "URL": "https://www.amazon.co.jp/dp/4839974713?tag=99hatena-22&linkCode=ogi&th=1&psc=1",
  "ImageURL": "https://m.media-amazon.com/images/I/51-TFmlxKJL.jpg",
  "Publisher": "マイナビ出版",
  "Contributor": "遠山 雄亮(著)",
  "Booktype": "文庫",
  "Title": "将棋・ひと目の詰み ~実戦形で終盤力アップ~ (マイナビ将棋文庫)",
  "Price": 1474,
  "Category": "将棋,Featured Categories",
  "Points": 15
 },
 {
  "Asin": "4065220440",
  "URL": "https://www.amazon.co.jp/dp/4065220440?tag=99hatena-22&linkCode=ogi&th=1&psc=1",
  "ImageURL": "なし",
  "Publisher": "講談社",
  "Contributor": "権左 武志(著)",
  "Booktype": "単行本（ソフトカバー）",
  "Title": "現代民主主義 思想と歴史 (講談社選書メチエ)",
  "Price": 2035,
  "Category": "ジャンル別,Featured Categories",
  "Points": 20
 },
 {
  "Asin": "4065220432",
  "URL": "https://www.amazon.co.jp/dp/4065220432?tag=99hatena-22&linkCode=ogi&th=1&psc=1",
  "ImageURL": "なし",
  "Publisher": "講談社",
  "Contributor": "宮下 志朗(著)",
  "Booktype": "文庫",
  "Title": "パリ歴史探偵 (講談社学術文庫)",
  "Price": 1155,
  "Category": "ジャンル別,Featured Categories",
  "Points": 12
 },
 {
  "Asin": "4065220459",
  "URL": "https://www.amazon.co.jp/dp/4065220459?tag=99hatena-22&linkCode=ogi&th=1&psc=1",
  "ImageURL": "なし",
  "Publisher": "講談社",
  "Contributor": "樺山 紘一(著)",
  "Booktype": "文庫",
  "Title": "《英雄》の世紀 ベートーヴェンと近代の創成者たち (講談社学術文庫)",
  "Price": 1012,
  "Category": "哲学・思想,Featured Categories",
  "Points": 10
 },
 {
  "Asin": "4492046801",
  "URL": "https://www.amazon.co.jp/dp/4492046801?tag=99hatena-22&linkCode=ogi&th=1&psc=1",
  "ImageURL": "なし",
  "Publisher": "東洋経済新報社",
  "Contributor": "スチュワート ロス(著)",
  "Booktype": "単行本",
  "Title": "なんでも「はじめて」大全: 人類と発明の物語",
  "Price": 2200,
  "Category": "ジャンル別",
  "Points": 22
 },
 {
  "Asin": "4065219078",
  "URL": "https://www.amazon.co.jp/dp/4065219078?tag=99hatena-22&linkCode=ogi&th=1&psc=1",
  "ImageURL": "なし",
  "Publisher": "講談社",
  "Contributor": "氣賀澤 保規(著)",
  "Booktype": "文庫",
  "Title": "中国の歴史6 絢爛たる世界帝国 隋唐時代 (講談社学術文庫)",
  "Price": 1485,
  "Category": "ジャンル別,Featured Categories",
  "Points": 15
 },
 {
  "Asin": "4065219108",
  "URL": "https://www.amazon.co.jp/dp/4065219108?tag=99hatena-22&linkCode=ogi&th=1&psc=1",
  "ImageURL": "なし",
  "Publisher": "講談社",
  "Contributor": "田中 美知太郎(著)",
  "Booktype": "文庫",
  "Title": "古代哲学史 (講談社学術文庫)",
  "Price": 1298,
  "Category": "哲学・思想,Featured Categories",
  "Points": 13
 },
 {
  "Asin": "406521906X",
  "URL": "https://www.amazon.co.jp/dp/406521906X?tag=99hatena-22&linkCode=ogi&th=1&psc=1",
  "ImageURL": "なし",
  "Publisher": "講談社",
  "Contributor": "川本 芳昭(著)",
  "Booktype": "文庫",
  "Title": "中国の歴史5 中華の崩壊と拡大 魏晋南北朝 (講談社学術文庫)",
  "Price": 1430,
  "Category": "ジャンル別,Featured Categories",
  "Points": 14
 },
 {
  "Asin": "4065219035",
  "URL": "https://www.amazon.co.jp/dp/4065219035?tag=99hatena-22&linkCode=ogi&th=1&psc=1",
  "ImageURL": "なし",
  "Publisher": "講談社",
  "Contributor": "渋沢 栄一(著)",
  "Booktype": "文庫",
  "Title": "渋沢栄一「青淵論叢」 道徳経済合一説 (講談社学術文庫)",
  "Price": 1386,
  "Category": "ジャンル別,Featured Categories",
  "Points": 14
 },
 {
  "Asin": "4092272391",
  "URL": "https://www.amazon.co.jp/dp/4092272391?tag=99hatena-22&linkCode=ogi&th=1&psc=1",
  "ImageURL": "なし",
  "Publisher": "小学館",
  "Contributor": "読売KODOMO新聞編集室(著)",
  "Booktype": "単行本",
  "Title": "名探偵コナン KODOMO時事ワード2021",
  "Price": 1078,
  "Category": "ジャンル別",
  "Points": 11
 },
 {
  "Asin": "4756254071",
  "URL": "https://www.amazon.co.jp/dp/4756254071?tag=99hatena-22&linkCode=ogi&th=1&psc=1",
  "ImageURL": "https://m.media-amazon.com/images/I/5199N8n2xzL.jpg",
  "Publisher": "パイインターナショナル",
  "Contributor": "アンヌ・ソフィ・ボマン(著)",
  "Booktype": "単行本（ソフトカバー）",
  "Title": "つくってみよう! ケーキやさん",
  "Price": 1870,
  "Category": "絵本",
  "Points": 19
 },
 {
  "Asin": "4864107947",
  "URL": "https://www.amazon.co.jp/dp/4864107947?tag=99hatena-22&linkCode=ogi&th=1&psc=1",
  "ImageURL": "なし",
  "Publisher": "飛鳥新社",
  "Contributor": "只野 範夫(著)",
  "Booktype": "文庫",
  "Title": "完全版 無税入門 文庫版",
  "Price": 800,
  "Category": "ビジネス・経済,Featured Categories",
  "Points": 8
 },
 {
  "Asin": "4798623733",
  "URL": "https://www.amazon.co.jp/dp/4798623733?tag=99hatena-22&linkCode=ogi&th=1&psc=1",
  "ImageURL": "なし",
  "Publisher": "ホビージャパン",
  "Contributor": "",
  "Booktype": "ムック",
  "Title": "Cameraholics Vol.4 (ホビージャパンMOOK 1049)",
  "Price": 2970,
  "Category": "カメラ・ビデオ,雑誌",
  "Points": 30
 },
 {
  "Asin": "4895315762",
  "URL": "https://www.amazon.co.jp/dp/4895315762?tag=99hatena-22&linkCode=ogi&th=1&psc=1",
  "ImageURL": "なし",
  "Publisher": "緑書房",
  "Contributor": "藤井 仁美(著)",
  "Booktype": "単行本",
  "Title": "猫の困った行動 予防&解決ブック",
  "Price": 1980,
  "Category": "猫",
  "Points": 20
 },
 {
  "Asin": "4895315797",
  "URL": "https://www.amazon.co.jp/dp/4895315797?tag=99hatena-22&linkCode=ogi&th=1&psc=1",
  "ImageURL": "https://m.media-amazon.com/images/I/41ju1+a9vdL.jpg",
  "Publisher": "緑書房",
  "Contributor": "楠田 哲士(著)",
  "Booktype": "単行本",
  "Title": "神の鳥ライチョウの生態と保全: 日本の宝を未来へつなぐ",
  "Price": 5280,
  "Category": "鳥類学",
  "Points": 53
 },
 {
  "Asin": "4839974748",
  "URL": "https://www.amazon.co.jp/dp/4839974748?tag=99hatena-22&linkCode=ogi&th=1&psc=1",
  "ImageURL": "https://m.media-amazon.com/images/I/51JcIbd3grL.jpg",
  "Publisher": "マイナビ出版",
  "Contributor": "結城聡(著)",
  "Booktype": "単行本（ソフトカバー）",
  "Title": "武闘派棋士・結城聡が教える 囲碁 戦いの考え方 (囲碁人ブックス)",
  "Price": 1749,
  "Category": "囲碁",
  "Points": 30
 },
 {
  "Asin": "4265049451",
  "URL": "https://www.amazon.co.jp/dp/4265049451?tag=99hatena-22&linkCode=ogi&th=1&psc=1",
  "ImageURL": "https://m.media-amazon.com/images/I/51kigKrRKUL.jpg",
  "Publisher": "岩崎書店",
  "Contributor": "巣山 ひろみ(著)",
  "Booktype": "単行本",
  "Title": "ちょいこわ ちょびっとこわーいはなし (5) 石の耳",
  "Price": 1100,
  "Category": "ホラー・怖い話",
  "Points": 11
 },
 {
  "Asin": "4265074839",
  "URL": "https://www.amazon.co.jp/dp/4265074839?tag=99hatena-22&linkCode=ogi&th=1&psc=1",
  "ImageURL": "https://m.media-amazon.com/images/I/61qVuAM7-rL.jpg",
  "Publisher": "岩崎書店",
  "Contributor": "友永 コリエ(著)",
  "Booktype": "単行本",
  "Title": "にじいろフェアリーしずくちゃん3 ようこそ! スクールフェスティバル",
  "Price": 1078,
  "Category": "童話・文学",
  "Points": 18
 },
 {
  "Asin": "426504946X",
  "URL": "https://www.amazon.co.jp/dp/426504946X?tag=99hatena-22&linkCode=ogi&th=1&psc=1",
  "ImageURL": "https://m.media-amazon.com/images/I/51iZj5nk0JL.jpg",
  "Publisher": "岩崎書店",
  "Contributor": "次良丸 忍(著)",
  "Booktype": "単行本",
  "Title": "ちょいこわ ちょびっとこわーいはなし (6) ゴミの人",
  "Price": 1100,
  "Category": "ホラー・怖い話",
  "Points": 11
 },
 {
  "Asin": "4839974942",
  "URL": "https://www.amazon.co.jp/dp/4839974942?tag=99hatena-22&linkCode=ogi&th=1&psc=1",
  "ImageURL": "https://m.media-amazon.com/images/I/51Wy+MzYUtL.jpg",
  "Publisher": "マイナビ出版",
  "Contributor": "真田圭一(著)",
  "Booktype": "単行本（ソフトカバー）",
  "Title": "1手ずつ解説する角換わり棒銀 (マイナビ将棋BOOKS)",
  "Price": 1694,
  "Category": "将棋",
  "Points": 30
 },
 {
  "Asin": "4098503654",
  "URL": "https://www.amazon.co.jp/dp/4098503654?tag=99hatena-22&linkCode=ogi&th=1&psc=1",
  "ImageURL": "なし",
  "Publisher": "小学館",
  "Contributor": "麻生 羽呂(著)",
  "Booktype": "コミック",
  "Title": "今際の国のアリス RETRY (1)",
  "Price": 499,
  "Category": "コミック",
  "Points": 5
 },
 {
  "Asin": "4065218179",
  "URL": "https://www.amazon.co.jp/dp/4065218179?tag=99hatena-22&linkCode=ogi&th=1&psc=1",
  "ImageURL": "なし",
  "Publisher": "講談社",
  "Contributor": "五条 まあさっちん(著)",
  "Booktype": "単行本（ソフトカバー）",
  "Title": "いつもの「おうちごはん」が特別になるレシピ 手抜きでも、大人も子どもも盛り上がる!",
  "Price": 1540,
  "Category": "ジャンル別",
  "Points": 15
 },
 {
  "Asin": "414072157X",
  "URL": "https://www.amazon.co.jp/dp/414072157X?tag=99hatena-22&linkCode=ogi&th=1&psc=1",
  "ImageURL": "なし",
  "Publisher": "NHK出版",
  "Contributor": "一般財団法人家電製品協会(編集)",
  "Booktype": "単行本",
  "Title": "家電製品エンジニア資格 AV情報家電の基礎と製品技術 2021年版",
  "Price": 3740,
  "Category": "ジャンル別",
  "Points": 37
 },
 {
  "Asin": "4295404845",
  "URL": "https://www.amazon.co.jp/dp/4295404845?tag=99hatena-22&linkCode=ogi&th=1&psc=1",
  "ImageURL": "なし",
  "Publisher": "クロスメディア・パブリッシング(インプレス)",
  "Contributor": "中村 浩介(著)",
  "Booktype": "単行本（ソフトカバー）",
  "Title": "クリニック起業術ー歯科医院開業ロケットスタートの極意",
  "Price": 2398,
  "Category": "その他",
  "Points": 24
 },
 {
  "Asin": "4295404837",
  "URL": "https://www.amazon.co.jp/dp/4295404837?tag=99hatena-22&linkCode=ogi&th=1&psc=1",
  "ImageURL": "なし",
  "Publisher": "クロスメディア・パブリッシング(インプレス)",
  "Contributor": "寺田 有希(著)",
  "Booktype": "単行本（ソフトカバー）",
  "Title": "対峙力",
  "Price": 1518,
  "Category": "仕事術・整理法",
  "Points": 26
 },
 {
  "Asin": "4140721545",
  "URL": "https://www.amazon.co.jp/dp/4140721545?tag=99hatena-22&linkCode=ogi&th=1&psc=1",
  "ImageURL": "なし",
  "Publisher": "NHK出版",
  "Contributor": "一般財団法人家電製品協会(編集)",
  "Booktype": "単行本",
  "Title": "家電製品アドバイザー資格 生活家電 商品知識と取扱い 2021年版",
  "Price": 2530,
  "Category": "家電製品アドバイザー",
  "Points": 25
 },
 {
  "Asin": "4862555799",
  "URL": "https://www.amazon.co.jp/dp/4862555799?tag=99hatena-22&linkCode=ogi&th=1&psc=1",
  "ImageURL": "なし",
  "Publisher": "カンゼン",
  "Contributor": "今泉忠明(監修)",
  "Booktype": "単行本（ソフトカバー）",
  "Title": "胸きゅん! 恋するいきもの図鑑",
  "Price": 1320,
  "Category": "図鑑・事典・年鑑",
  "Points": 13
 },
 {
  "Asin": "4140721537",
  "URL": "https://www.amazon.co.jp/dp/4140721537?tag=99hatena-22&linkCode=ogi&th=1&psc=1",
  "ImageURL": "なし",
  "Publisher": "NHK出版",
  "Contributor": "一般財団法人家電製品協会(編集)",
  "Booktype": "単行本",
  "Title": "家電製品アドバイザー資格 AV情報家電 商品知識と取扱い 2021年版",
  "Price": 2640,
  "Category": "家電製品アドバイザー",
  "Points": 26
 },
 {
  "Asin": "4140721588",
  "URL": "https://www.amazon.co.jp/dp/4140721588?tag=99hatena-22&linkCode=ogi&th=1&psc=1",
  "ImageURL": "なし",
  "Publisher": "NHK出版",
  "Contributor": "一般財団法人家電製品協会(編集)",
  "Booktype": "単行本",
  "Title": "家電製品エンジニア資格 生活家電の基礎と製品技術 2021年版",
  "Price": 3740,
  "Category": "ジャンル別",
  "Points": 37
 },
 {
  "Asin": "4140721561",
  "URL": "https://www.amazon.co.jp/dp/4140721561?tag=99hatena-22&linkCode=ogi&th=1&psc=1",
  "ImageURL": "なし",
  "Publisher": "NHK出版",
  "Contributor": "一般財団法人家電製品協会(編集)",
  "Booktype": "単行本",
  "Title": "家電製品アドバイザー資格 問題&解説集 2021年版",
  "Price": 1760,
  "Category": "家電製品アドバイザー",
  "Points": 18
 },
 {
  "Asin": "4140721553",
  "URL": "https://www.amazon.co.jp/dp/4140721553?tag=99hatena-22&linkCode=ogi&th=1&psc=1",
  "ImageURL": "なし",
  "Publisher": "NHK出版",
  "Contributor": "一般財団法人家電製品協会(編集)",
  "Booktype": "単行本",
  "Title": "家電製品アドバイザー資格 CSと関連法規 2021年版",
  "Price": 1980,
  "Category": "投資・金融・会社経営,家電製品アドバイザー",
  "Points": 20
 },
 {
  "Asin": "4582842364",
  "URL": "https://www.amazon.co.jp/dp/4582842364?tag=99hatena-22&linkCode=ogi&th=1&psc=1",
  "ImageURL": "なし",
  "Publisher": "平凡社",
  "Contributor": "瀬田 勝哉(著)",
  "Booktype": "単行本",
  "Title": "戦争が巨木を伐った: 太平洋戦争と供木運動・木造船 (236)",
  "Price": 4950,
  "Category": "ジャンル別",
  "Points": 90
 },
 {
  "Asin": "4140721596",
  "URL": "https://www.amazon.co.jp/dp/4140721596?tag=99hatena-22&linkCode=ogi&th=1&psc=1",
  "ImageURL": "なし",
  "Publisher": "NHK出版",
  "Contributor": "一般財団法人家電製品協会(編集)",
  "Booktype": "単行本",
  "Title": "家電製品エンジニア資格 問題&解説集 2021年版",
  "Price": 2090,
  "Category": "ジャンル別",
  "Points": 21
 },
 {
  "Asin": "4895315800",
  "URL": "https://www.amazon.co.jp/dp/4895315800?tag=99hatena-22&linkCode=ogi&th=1&psc=1",
  "ImageURL": "https://m.media-amazon.com/images/I/51lWmuV7UyL.jpg",
  "Publisher": "緑書房",
  "Contributor": "武田 康男(著)",
  "Booktype": "単行本",
  "Title": "楽しい雪の結晶観察図鑑",
  "Price": 2090,
  "Category": "地球科学",
  "Points": 21
 },
 {
  "Asin": "4140072717",
  "URL": "https://www.amazon.co.jp/dp/4140072717?tag=99hatena-22&linkCode=ogi&th=1&psc=1",
  "ImageURL": "なし",
  "Publisher": "NHK出版",
  "Contributor": "NHK放送文化研究所(編集)",
  "Booktype": "単行本",
  "Title": "NHK年鑑2020",
  "Price": 7370,
  "Category": "ジャンル別",
  "Points": 74
 },
 {
  "Asin": "4863135025",
  "URL": "https://www.amazon.co.jp/dp/4863135025?tag=99hatena-22&linkCode=ogi&th=1&psc=1",
  "ImageURL": "なし",
  "Publisher": "日経ナショナルジオグラフィック社",
  "Contributor": "三井 昌志(著)",
  "Booktype": "単行本（ソフトカバー）",
  "Title": "Colorful Life 幸せな色を探して",
  "Price": 2420,
  "Category": "写真家",
  "Points": 24
 },
 {
  "Asin": "484709994X",
  "URL": "https://www.amazon.co.jp/dp/484709994X?tag=99hatena-22&linkCode=ogi&th=1&psc=1",
  "ImageURL": "https://m.media-amazon.com/images/I/51yIYt0jMvL.jpg",
  "Publisher": "ワニブックス",
  "Contributor": "キム・スヒョン(著)",
  "Booktype": "単行本（ソフトカバー）",
  "Title": "頑張りすぎずに、気楽に - お互いが幸せに生きるためのバランスを探して -",
  "Price": 1540,
  "Category": "その他",
  "Points": 28
 },
 {
  "Asin": "453232372X",
  "URL": "https://www.amazon.co.jp/dp/453232372X?tag=99hatena-22&linkCode=ogi&th=1&psc=1",
  "ImageURL": "なし",
  "Publisher": "日本経済新聞出版",
  "Contributor": "日本M&Aセンター海外事業部(著)",
  "Booktype": "単行本（ソフトカバー）",
  "Title": "ASEAN M&A時代の幕開け 中堅・中小企業の成長戦略を描く",
  "Price": 1650,
  "Category": "中小企業経営,投資・金融・会社経営",
  "Points": 17
 },
 {
  "Asin": "4532323746",
  "URL": "https://www.amazon.co.jp/dp/4532323746?tag=99hatena-22&linkCode=ogi&th=1&psc=1",
  "ImageURL": "なし",
  "Publisher": "日本経済新聞出版",
  "Contributor": "山浦 雄一(著)",
  "Booktype": "単行本（ソフトカバー）",
  "Title": "現場の判断、経営の判断 宇宙開発に見るリスク対応",
  "Price": 2090,
  "Category": "危機管理",
  "Points": 38
 },
 {
  "Asin": "486240183X",
  "URL": "https://www.amazon.co.jp/dp/486240183X?tag=99hatena-22&linkCode=ogi&th=1&psc=1",
  "ImageURL": "なし",
  "Publisher": "産業環境管理協会",
  "Contributor": "長岡 文明(著)",
  "Booktype": "単行本",
  "Title": "ここまでわかる! 廃棄物処理法問題集 改訂第2版",
  "Price": 3300,
  "Category": "ジャンル別",
  "Points": 33
 },
 {
  "Asin": "4861107148",
  "URL": "https://www.amazon.co.jp/dp/4861107148?tag=99hatena-22&linkCode=ogi&th=1&psc=1",
  "ImageURL": "なし",
  "Publisher": "春風社",
  "Contributor": "菊池清明(編集)",
  "Booktype": "単行本",
  "Title": "中世英語英文学研究の多様性とその展望: 吉野利弘先生 山内一芳先生 喜寿記念論文集",
  "Price": 8800,
  "Category": "ジャンル別",
  "Points": 88
 },
 {
  "Asin": "4815609101",
  "URL": "https://www.amazon.co.jp/dp/4815609101?tag=99hatena-22&linkCode=ogi&th=1&psc=1",
  "ImageURL": "なし",
  "Publisher": "SBクリエイティブ",
  "Contributor": "えぞぎんぎつね(著)",
  "Booktype": "文庫",
  "Title": "神殺しの魔王、最弱種族に転生し史上最強になる (GA文庫)",
  "Price": 770,
  "Category": "ライトノベル,Featured Categories",
  "Points": 14
 },
 {
  "Asin": "4815607818",
  "URL": "https://www.amazon.co.jp/dp/4815607818?tag=99hatena-22&linkCode=ogi&th=1&psc=1",
  "ImageURL": "なし",
  "Publisher": "SBクリエイティブ",
  "Contributor": "三河ごーすと(著)",
  "Booktype": "文庫",
  "Title": "友達の妹が俺にだけウザい6 (GA文庫)",
  "Price": 770,
  "Category": "ライトノベル,Featured Categories",
  "Points": 14
 },
 {
  "Asin": "4502367516",
  "URL": "https://www.amazon.co.jp/dp/4502367516?tag=99hatena-22&linkCode=ogi&th=1&psc=1",
  "ImageURL": "なし",
  "Publisher": "中央経済社",
  "Contributor": "西村 明(著)",
  "Booktype": "単行本",
  "Title": "管理会計の挑戦: リスク・スラック・バランス",
  "Price": 7480,
  "Category": "ジャンル別",
  "Points": 75
 },
 {
  "Asin": "4815608326",
  "URL": "https://www.amazon.co.jp/dp/4815608326?tag=99hatena-22&linkCode=ogi&th=1&psc=1",
  "ImageURL": "なし",
  "Publisher": "SBクリエイティブ",
  "Contributor": "進行諸島(著)",
  "Booktype": "文庫",
  "Title": "殲滅魔導の最強賢者2 無才の賢者、魔導を極め最強へ至る (GA文庫)",
  "Price": 770,
  "Category": "ライトノベル,コミック,Featured Categories",
  "Points": 14
 },
 {
  "Asin": "4815609225",
  "URL": "https://www.amazon.co.jp/dp/4815609225?tag=99hatena-22&linkCode=ogi&th=1&psc=1",
  "ImageURL": "https://m.media-amazon.com/images/I/51adJDnUb9L.jpg",
  "Publisher": "SBクリエイティブ",
  "Contributor": "有澤有(著)",
  "Booktype": "文庫",
  "Title": "魔王と聖女が導く冒険者ライフ2 -魔法適性0だけど極大魔力に覚醒しました- (GA文庫)",
  "Price": 748,
  "Category": "ライトノベル,Featured Categories",
  "Points": 7
 },
 {
  "Asin": "4098607786",
  "URL": "https://www.amazon.co.jp/dp/4098607786?tag=99hatena-22&linkCode=ogi&th=1&psc=1",
  "ImageURL": "なし",
  "Publisher": "小学館",
  "Contributor": "魚豊(著)",
  "Booktype": "コミック",
  "Title": "チ。―地球の運動について― (1)",
  "Price": 650,
  "Category": "コミック",
  "Points": 7
 },
 {
  "Asin": "4299009274",
  "URL": "https://www.amazon.co.jp/dp/4299009274?tag=99hatena-22&linkCode=ogi&th=1&psc=1",
  "ImageURL": "なし",
  "Publisher": "宝島社",
  "Contributor": "",
  "Booktype": "大型本",
  "Title": "moz 整理上手な本革コンパクト財布BOOK (ブランドブック)",
  "Price": 1969,
  "Category": "ファッション",
  "Points": 34
 },
 {
  "Asin": "4560088888",
  "URL": "https://www.amazon.co.jp/dp/4560088888?tag=99hatena-22&linkCode=ogi&th=1&psc=1",
  "ImageURL": "なし",
  "Publisher": "白水社",
  "Contributor": "上田 広美(著)",
  "Booktype": "単行本（ソフトカバー）",
  "Title": "ニューエクスプレスプラス カンボジア語《CD付》",
  "Price": 3300,
  "Category": "その他の外国語",
  "Points": 33
 }
]